Metadata-Version: 2.4
Name: orthoseg
Version: 0.7.0
Summary: Package to make it easier to segment orthophotos.
Home-page: https://github.com/orthoseg/orthoseg
Author: Pieter Roggemans
Author-email: pieter.roggemans@gmail.com
Classifier: Programming Language :: Python :: 3
Classifier: Operating System :: OS Independent
Requires-Python: >=3.10
License-File: LICENSE.MD
Requires-Dist: gdal
Requires-Dist: gdown
Requires-Dist: geofileops>=0.10
Requires-Dist: geopandas>=1.0
Requires-Dist: matplotlib
Requires-Dist: numpy
Requires-Dist: owslib
Requires-Dist: pillow
Requires-Dist: pycron
Requires-Dist: pygeoops>=0.4
Requires-Dist: rasterio
Requires-Dist: segmentation-models<1.1,>=1.0
Requires-Dist: shapely>=2
Requires-Dist: simplification
Requires-Dist: tensorflow>=2.8
Dynamic: author
Dynamic: author-email
Dynamic: classifier
Dynamic: description
Dynamic: description-content-type
Dynamic: home-page
Dynamic: license-file
Dynamic: requires-dist
Dynamic: requires-python
Dynamic: summary
